aiconfig_extension_hugging_face_transformers/__init__.py
aiconfig_extension_hugging_face_transformers/text_generation.py
aiconfig_extension_hugging_face_transformers-0.0.4.dist-info/LICENSE
aiconfig_extension_hugging_face_transformers-0.0.4.dist-info/METADATA
aiconfig_extension_hugging_face_transformers-0.0.4.dist-info/WHEEL
aiconfig_extension_hugging_face_transformers-0.0.4.dist-info/top_level.txt
aiconfig_extension_hugging_face_transformers-0.0.4.dist-info/RECORD
