Metadata-Version: 2.1
Name: aiconfig_extension_hugging_face_transformers
Version: 0.0.4
Summary: An extension for using Hugging Face transformers to parse models for AIConfig.
Author: LastMile AI
Author-email: Rossdan Craig <rossdan@lastmileai.dev>, Ankush Pala <ankush@lastmileai.dev>
Project-URL: Homepage, https://github.com/lastmile-ai/aiconfig/
Project-URL: Issues, https://github.com/lastmile-ai/aiconfig/issues
Classifier: Programming Language :: Python :: 3
Classifier: License :: OSI Approved :: MIT License
Classifier: Operating System :: OS Independent
Requires-Python: >=3.8
License-File: LICENSE
Requires-Dist: black
Requires-Dist: pylint
Requires-Dist: python-aiconfig
Requires-Dist: transformers
Requires-Dist: torch
Requires-Dist: torchvision
Requires-Dist: torchaudio
Requires-Dist: asyncio
